sphinxcontrib_golangdomain-0.2.0.dev0-py3.6-nspkg.pth
sphinxcontrib/golangdomain.py
sphinxcontrib_golangdomain-0.2.0.dev0.dist-info/METADATA
sphinxcontrib_golangdomain-0.2.0.dev0.dist-info/RECORD
sphinxcontrib_golangdomain-0.2.0.dev0.dist-info/WHEEL
sphinxcontrib_golangdomain-0.2.0.dev0.dist-info/namespace_packages.txt
sphinxcontrib_golangdomain-0.2.0.dev0.dist-info/top_level.txt
