Metadata-Version: 2.1
Name: sphinxcontrib-golangdomain
Version: 0.2.0.dev0
Summary: Sphinx extension sphinxcontrib-golangdomain
Home-page: http://bitbucket.org/ymotongpoo/sphinxcontrib-golangdomain
Author: Yoshifumi YAMAGUCHI
Author-email: ymotongpoo@gmail.com
License: BSD
Download-URL: http://pypi.python.org/pypi/sphinxcontrib-golangdomain
Platform: any
Classifier: Development Status :: 4 - Beta
Classifier: Environment :: Console
Classifier: Environment :: Web Environment
Classifier: Intended Audience :: Developers
Classifier: License :: OSI Approved :: BSD License
Classifier: Operating System :: OS Independent
Classifier: Programming Language :: Python
Classifier: Topic :: Documentation
Classifier: Topic :: Utilities
Requires-Dist: Sphinx (>=1.0)
